plib/stdlib/__init__.py
plib/stdlib/_extras.py
plib/stdlib/builtins.py
plib/stdlib/classtools.py
plib/stdlib/cmdline.py
plib/stdlib/copytools.py
plib/stdlib/csvtools.py
plib/stdlib/enumtools.py
plib/stdlib/examples.py
plib/stdlib/fdtools.py
plib/stdlib/imp.py
plib/stdlib/iters.py
plib/stdlib/jsontools.py
plib/stdlib/localize.py
plib/stdlib/mail.py
plib/stdlib/mathlib.py
plib/stdlib/options.py
plib/stdlib/ostools.py
plib/stdlib/postinstall.py
plib/stdlib/proc.py
plib/stdlib/sigs.py
plib/stdlib/strings.py
plib/stdlib/systools.py
plib/stdlib/timer.py
plib/stdlib/tztools.py
plib/stdlib/coll/__init__.py
plib/stdlib/coll/_abc.py
plib/stdlib/coll/_bases.py
plib/stdlib/coll/_mixins.py
plib/stdlib/coll/_names.py
plib/stdlib/coll/_seq.py
plib/stdlib/coll/_tests.py
plib/stdlib/coll/_tuples.py
plib/stdlib/coll/_utils.py
plib/stdlib/decotools/DelayedDecorator.py
plib/stdlib/decotools/IndexedGenerator.py
plib/stdlib/decotools/MemoizedGenerator.py
plib/stdlib/decotools/__init__.py
plib/stdlib/ini/PIniFile.py
plib/stdlib/ini/PIniFileBase.py
plib/stdlib/ini/PIniFileOption.py
plib/stdlib/ini/PIniFileSection.py
plib/stdlib/ini/PIniInterface.py
plib/stdlib/ini/__init__.py
plib/stdlib/net/__init__.py
plib/stdlib/net/client.py
plib/stdlib/net/transport.py
plib/test/__main__.py
plib/test/stdlib/ModuleProxy_testmod.py
plib/test/stdlib/__init__.py
plib/test/stdlib/__main__.py
plib/test/stdlib/abstract_testlib.py
plib/test/stdlib/mapping_testlib.py
plib/test/stdlib/test_ModuleProxy.py
plib/test/stdlib/test_abstractcontainer.py
plib/test/stdlib/test_abstractdict.py
plib/test/stdlib/test_abstractkeyed.py
plib/test/stdlib/test_abstractlist.py
plib/test/stdlib/test_abstractmapping.py
plib/test/stdlib/test_abstractsequence.py
plib/test/stdlib/test_basecontainer.py
plib/test/stdlib/test_basedict.py
plib/test/stdlib/test_basekeyed.py
plib/test/stdlib/test_baselist.py
plib/test/stdlib/test_basemapping.py
plib/test/stdlib/test_basesequence.py
plib/test/stdlib/test_ostools.py
plib3.stdlib-2.4.dist-info/LICENSE.txt
plib3.stdlib-2.4.dist-info/METADATA
plib3.stdlib-2.4.dist-info/WHEEL
plib3.stdlib-2.4.dist-info/entry_points.txt
plib3.stdlib-2.4.dist-info/top_level.txt
plib3.stdlib-2.4.dist-info/RECORD
