Metadata-Version: 2.1
Name: plib3.stdlib
Version: 2.4
Summary: Useful packages and modules to extend the Python 3 standard library.
Home-page: http://pypi.org/project/plib3.stdlib
Author: Peter A. Donis
Author-email: peterdonis@alum.mit.edu
License: GPLv2
Classifier: Development Status :: 5 - Production/Stable
Classifier: Environment :: Console
Classifier: Environment :: MacOS X
Classifier: Environment :: Win32 (MS Windows)
Classifier: Intended Audience :: Developers
Classifier: License :: OSI Approved :: GNU General Public License v2 (GPLv2)
Classifier: Operating System :: MacOS :: MacOS X
Classifier: Operating System :: Microsoft :: Windows
Classifier: Operating System :: POSIX
Classifier: Operating System :: POSIX :: Linux
Classifier: Programming Language :: Python :: 3
Classifier: Topic :: Software Development :: Libraries :: Python Modules
Requires-Python: >=3.8
License-File: LICENSE.txt
